lightgrad/__init__.py
lightgrad/engine.cp39-win_amd64.pyd
lightgrad/nn.py
lightgrad-0.0.2.dist-info/LICENSE
lightgrad-0.0.2.dist-info/METADATA
lightgrad-0.0.2.dist-info/WHEEL
lightgrad-0.0.2.dist-info/top_level.txt
lightgrad-0.0.2.dist-info/RECORD
