Metadata-Version: 2.1
Name: lightgrad
Version: 0.0.2
Summary: Autograd Engine written in Python C-API
Home-page: https://github.com/marcosalvalaggio-bip/lightgrad
Author: Marco S.
Author-email: mar.salvalaggio@gmail.com
License: MIT
Classifier: Programming Language :: Python :: 3
Classifier: License :: OSI Approved :: MIT License
Classifier: Operating System :: OS Independent
Requires-Python: >=3.6
License-File: LICENSE
